{
    "link2": {
        "link": "https://youtube.com/shorts/bJocWv4utdg",
        "id": "bJocWv4utdg",
        "title": "Veja os novos dispositivos Androids que deixará de suportar o WhatsApp."
    },
    "link3": {
        "link": "https://youtu.be/z77fnbAC8Yc",
        "id": "z77fnbAC8Yc",
        "title": "O WhatsApp irá parar nesses Androids em 2025. NOVA LISTA!!!"
    },
    "link1": {
        "link": "https://youtu.be/O4RbY_70g8E",
        "id": "O4RbY_70g8E",
        "title": "Atualize o seu iPhone AGORA!!!"
    }
}