{
    "link3": {
        "link": "https://youtube.com/shorts/VTrNNLfV52g",
        "id": "VTrNNLfV52g",
        "title": "Veja: Como colocar o seu smartphone para carregar corretamente."
    },
    "link1": {
        "link": "https://youtube.com/shorts/q4WfucBa6fw",
        "id": "q4WfucBa6fw",
        "title": "O WhatsApp não dará suporte a versões anteriores ao iOS 15.1"
    },
    "link2": {
        "link": "https://youtu.be/pFLrZa4mTEQ",
        "id": "pFLrZa4mTEQ",
        "title": "O WhatsApp irá parar nesses iPhones em 2025"
    }
}